vimala/__init__.py
vimala/_vim.py
vimala/py.typed
vimala/pytest_plugin.py
vimala-0.2.0.dist-info/METADATA
vimala-0.2.0.dist-info/WHEEL
vimala-0.2.0.dist-info/top_level.txt
vimala-0.2.0.dist-info/RECORD
