Metadata-Version: 2.1
Name: vimala
Version: 0.2.0
Summary: Python library for working with command-line editors (like vim).
Home-page: https://github.com/bbugyi200/vimala
Author: Bryan M Bugyi
Author-email: bryanbugyi34@gmail.com
License: MIT license
Classifier: Development Status :: 3 - Alpha
Classifier: Intended Audience :: Developers
Classifier: License :: OSI Approved :: MIT License
Classifier: Natural Language :: English
Classifier: Programming Language :: Python :: 3
Classifier: Programming Language :: Python :: 3.9
Classifier: Programming Language :: Python :: 3.10
Classifier: Programming Language :: Python :: 3.11
Classifier: Programming Language :: Python :: 3.12
Requires-Python: >=3.9
Requires-Dist: bolton-proctor ~=0.2.1
Requires-Dist: bolton-typist ~=0.2.0
